MANIFEST.in
README.md
requirements.txt
setup.py
aquifer/__init__.py
aquifer/core.py
aquifer/test_core.py
aquifer.egg-info/PKG-INFO
aquifer.egg-info/SOURCES.txt
aquifer.egg-info/dependency_links.txt
aquifer.egg-info/requires.txt
aquifer.egg-info/top_level.txt
aquifer/backends/__init__.py
aquifer/backends/datadog_backend.py