Metadata-Version: 1.1
Name: aquifer
Version: 1.1.0
Summary: Metrics send/query abstraction layer with URI-based backend configuration
Home-page: https://github.com/bodylabs/aquifer
Author: Body Labs
Author-email: chenyang.liu@bodylabs.com
License: MIT
Platform: UNKNOWN
Classifier: Development Status :: 3 - Alpha
Classifier: Intended Audience :: Developers
Classifier: License :: OSI Approved :: MIT License
Classifier: Operating System :: OS Independent
Classifier: Programming Language :: Python
